flexfloat/__init__.py
flexfloat/core.py
flexfloat/py.typed
flexfloat/types.py
flexfloat/bitarray/__init__.py
flexfloat/bitarray/bitarray.py
flexfloat/bitarray/bitarray_bigint.py
flexfloat/bitarray/bitarray_bool.py
flexfloat/bitarray/bitarray_int64.py
flexfloat/bitarray/bitarray_mixins.py
flexfloat/math/__init__.py
flexfloat/math/constants.py
flexfloat/math/exponential.py
flexfloat/math/floating_point.py
flexfloat/math/hyperbolic.py
flexfloat/math/logarithmic.py
flexfloat/math/sqrt.py
flexfloat/math/trigonometric.py
flexfloat/math/utility.py
flexfloat-1.0.0.dist-info/licenses/LICENSE
flexfloat-1.0.0.dist-info/METADATA
flexfloat-1.0.0.dist-info/WHEEL
flexfloat-1.0.0.dist-info/top_level.txt
flexfloat-1.0.0.dist-info/RECORD
