Metadata-Version: 2.4
Name: flexfloat
Version: 1.0.0
Summary: A high-precision Python library for arbitrary precision floating-point arithmetic with growable exponents and fixed-size fractions
Author: Ferran Sanchez Llado
License: MIT
Classifier: Development Status :: 5 - Production/Stable
Classifier: Intended Audience :: Developers
Classifier: Intended Audience :: Science/Research
Classifier: License :: OSI Approved :: MIT License
Classifier: Operating System :: OS Independent
Classifier: Programming Language :: Python :: 3
Classifier: Programming Language :: Python :: 3.11
Classifier: Programming Language :: Python :: 3.12
Classifier: Programming Language :: Python :: 3.13
Classifier: Topic :: Scientific/Engineering :: Mathematics
Classifier: Topic :: Software Development :: Libraries :: Python Modules
Requires-Python: >=3.11
License-File: LICENSE
Provides-Extra: dev
Requires-Dist: pytest>=7.0; extra == "dev"
Requires-Dist: pytest-cov>=4.0; extra == "dev"
Requires-Dist: pytest-xdist>=3.0; extra == "dev"
Requires-Dist: black>=23.0; extra == "dev"
Requires-Dist: isort>=5.0; extra == "dev"
Requires-Dist: mypy>=1.0; extra == "dev"
Requires-Dist: pylint>=3.0; extra == "dev"
Requires-Dist: flake8>=6.0; extra == "dev"
Requires-Dist: bump2version>=1.0; extra == "dev"
Requires-Dist: build>=0.10; extra == "dev"
Requires-Dist: twine>=4.0; extra == "dev"
Requires-Dist: check-manifest>=0.49; extra == "dev"
Requires-Dist: PyYAML>=6.0; extra == "dev"
Provides-Extra: docs
Requires-Dist: sphinx>=7.0; extra == "docs"
Requires-Dist: sphinx-rtd-theme>=2.0; extra == "docs"
Requires-Dist: sphinx-copybutton>=0.5; extra == "docs"
Requires-Dist: myst-parser>=2.0; extra == "docs"
Requires-Dist: sphinx-autobuild>=2021.3.14; extra == "docs"
Requires-Dist: requests>=2.25.0; extra == "docs"
Dynamic: license-file
